mol_properties/__init__.py
mol_properties/__main__.py
mol_properties/calc.py
mol_properties/utils.py
mol_properties-1.0.4.dist-info/LICENSE
mol_properties-1.0.4.dist-info/LICENSE.txt
mol_properties-1.0.4.dist-info/METADATA
mol_properties-1.0.4.dist-info/WHEEL
mol_properties-1.0.4.dist-info/entry_points.txt
mol_properties-1.0.4.dist-info/top_level.txt
mol_properties-1.0.4.dist-info/RECORD
