Metadata-Version: 2.1
Name: mol-properties
Version: 1.0.4
Summary: CLI tool to calculate molecular properties and drug-likeness
Home-page: https://github.com/yourusername/mol-properties
Author: Your Name
Author-email: your.email@example.com
Classifier: Programming Language :: Python :: 3
Classifier: License :: OSI Approved :: MIT License
Classifier: Operating System :: OS Independent
Requires-Python: >=3.10
License-File: LICENSE
License-File: LICENSE.txt
Requires-Dist: pandas
